{
    "ants_from_up_there": {
        "title": "Ants From Up There",
        "artist": "Black Country, New Road",
        "score": 10,
        "rank": 8,
        "released": "02-04-2022",
        "reviewed": "09-10-2024"
    },
    "not_available": {
        "title": "Not Available",
        "artist": "The Residents",
        "score": 10,
        "rank": 10,
        "released": "10-31-1978",
        "reviewed": "09-18-2024"
    },
    "blood_visions": {
        "title": "Blood Visions",
        "artist": "Jay Reatard",
        "score": 10,
        "rank": 6,
        "released": "09-11-2006",
        "reviewed": "09-10-2024"
    },
    "congratulations": {
        "title": "Congratulations",
        "artist": "MGMT",
        "score": 10,
        "rank": 2,
        "released": "04-13-2010",
        "reviewed": "09-10-2024"
    },
    "girl_with_basket_of_fruit": {
        "title": "Girl with Basket of Fruit",
        "artist": "Xiu Xiu",
        "score": 10,
        "rank": 11,
        "released": "02-08-2019",
        "reviewed": "09-10-2024"
    },
    "lonesome_crowded_west": {
        "title": "The Lonesome Crowded West",
        "artist": "Modest Mouse",
        "score": 10,
        "rank": 4,
        "released": "09-18-1997",
        "reviewed": "09-10-2024"
    },
    "STGSTV": {
        "title": "Spirit They're Gone, Spirit They've Vanished",
        "artist": "Animal Collective",
        "score": 10,
        "rank": 1,
        "released": "07-31-2000",
        "reviewed": "09-10-2024"
    },
    "TVUandN": {
        "title": "The Velvet Underground & Nico",
        "artist": "The Velvet Underground & Nico",
        "score": 10,
        "rank": 9,
        "released": "03-12-1967",
        "reviewed": "09-10-2024"
    },
    "TPAB": {
        "title": "To Pimp a Butterfly",
        "artist": "Kendrick Lamar",
        "score": 10,
        "rank": 7,
        "released": "03-15-2015",
        "reviewed": "09-10-2024"
    },
    "to_be_kind": {
        "title": "To Be Kind",
        "artist": "Swans",
        "score": 10,
        "rank": 3,
        "released": "05-13-2014",
        "reviewed": "09-10-2024"
    },
    "skinny_fists": {
        "title": "Lift Your Skinny Fists Like Antennas to Heaven",
        "artist": "Godspeed You! Black Emperor",
        "score": 10,
        "rank": 5,
        "released": "10-09-2000",
        "reviewed": "09-10-2024"
    },
    "volcanic_bird_enemy": {
        "title": "volcanic bird enemy and the voiced concern",
        "artist": "Lil Ugly Mane",
        "score": 9.9,
        "released": "10-12-2021",
        "reviewed": "09-10-2024"
    },
    "love_streams": {
        "title": "Love Streams",
        "artist": "Tim Hecker",
        "score": 9.7,
        "released": "04-08-2016",
        "reviewed": "09-19-2024"
    },
    "divine_music": {
        "title": "Divine Music From a Jail",
        "artist": "Oidupaa Vladimir Oiun",
        "score": 9.4,
        "released": "12-31-1999",
        "reviewed": "09-19-2024"
    },
    "midnight_sun": {
        "title": "In the Midnight Sun or Stubbornly Persistent Illusion",
        "artist": "Golden Drugs",
        "score": 9.8,
        "released": "01-01-2015",
        "reviewed": "09-10-2024"
    },
    "fishmans_live": {
        "title": "98.12.28 男達の別れ (98.12.28 Otokotachi no wakare)",
        "artist": "Fishmans",
        "score": 9.6,
        "released": "09-29-1999",
        "reviewed": "09-19-2024"
    },
    "we_got_it_from_here": {
        "title": "We got it from Here… Thank You 4 Your service",
        "artist": "A Tribe Called Quest",
        "score": 9.7,
        "released": "11-11-2016",
        "reviewed": "09-19-2024"
    },
    "cavalcade": {
        "title": "Cavalcade",
        "artist": "black midi",
        "score": 9.5,
        "released": "05-26-2021",
        "reviewed": "09-19-2024"
    },
    "person_pitch": {
        "title": "Person Pitch",
        "artist": "Panda Bear",
        "score": 9.8,
        "released": "03-20-2007",
        "reviewed": "09-19-2024"
    },
    "watermusic_2": {
        "title": "Watermusic II",
        "artist": "William Basinski",
        "score": 8.6,
        "released": "07-15-2003",
        "reviewed": "09-18-2024"
    },
    "brat": {
        "title": "brat",
        "artist": "Charli XCX",
        "score": 9.1,
        "released": "07-07-2024",
        "reviewed": "09-20-2024"
    },
    "heaven_or": {
        "title": "Heaven or Las Vegas",
        "artist": "Cocteau Twins",
        "score": 9.3,
        "released": "09-17-1990",
        "reviewed": "10-04-2024"
    },
    "the_new_sound": {
        "title": "The New Sound",
        "artist": "Geordie Greep",
        "score": 9.8,
        "released": "10-04-2024",
        "reviewed": "10-06-2024"
    },
    "yots": {
        "title": "Year of the Snitch",
        "artist": "Death Grips",
        "score": 9.5,
        "released": "06-22-2018",
        "reviewed": "10-06-2024"
    },
    "burning_desire": {
        "title": "Burning Desire",
        "artist": "MIKE",
        "score": 8.9,
        "released": "10-13-2023",
        "reviewed": "10-06-2024"
    },
    "forced_witness": {
        "title": "Forced Witness",
        "artist": "Alex Cameron",
        "score": 9.7,
        "released": "09-08-2017",
        "reviewed": "10-06-2024"
    },
    "lz4": {
        "title": "Led Zeppelin IV",
        "artist": "Led Zeppelin",
        "score": 9.4,
        "released": "11-08-1971",
        "reviewed": "10-06-2024"
    },
    "kaputt": {
        "title": "Kaputt",
        "artist": "Destroyer",
        "score": 9.4,
        "released": "01-25-2011",
        "reviewed": "10-07-2024"
    },
    "three_love_songs": {
        "title": "Three Love Songs",
        "artist": "Ricky Eat Acid",
        "score": 9.3,
        "released": "01-21-2014",
        "reviewed": "10-08-2024"
    },
    "who_is_onyeabor": {
        "title": "Who is William Onyeabor",
        "artist": "William Onyeabor",
        "score": 8.7,
        "released": "10-15-2013",
        "reviewed": "10-07-2024"
    },
    "people_who_can": {
        "title": "People Who Can Eat People Are the Luckiest People in the World",
        "artist": "Andrew Jackson Jihad",
        "score": 9.2,
        "released": "08-31-2007",
        "reviewed": "10-08-2024"
    },
    "those_who_throw": {
        "title": "Those Who Throw Objects at the Crocodiles Will Be Asked to Retrieve Them",
        "artist": "Bruno Pernadas",
        "score": 8.4,
        "released": "09-23-2016",
        "reviewed": "10-08-2024"
    },
    "serial_parade": {
        "title": "Serial Parade EP",
        "artist": "Twin Steps",
        "score": 9.5,
        "released": "04-10-2012",
        "reviewed": "10-08-2024"
    }
}